LICENSE
MANIFEST.in
README.md
WAIVER
WAIVER.asc
requirements.txt
setup.cfg
setup.py
sql_requirements.txt
test_requirements.txt
funga/eth/__init__.py
funga/eth/encoding.py
funga/eth/message.py
funga/eth/transaction.py
funga/eth/cli/__init__.py
funga/eth/cli/handle.py
funga/eth/cli/http.py
funga/eth/cli/jsonrpc.py
funga/eth/cli/socket.py
funga/eth/data/config/database.ini
funga/eth/data/config/signer.ini
funga/eth/keystore/__init__.py
funga/eth/keystore/dict.py
funga/eth/keystore/interface.py
funga/eth/keystore/keyfile.py
funga/eth/keystore/sql.py
funga/eth/runnable/keyfile.py
funga/eth/runnable/msg.py
funga/eth/runnable/signer.py
funga/eth/signer/__init__.py
funga/eth/signer/defaultsigner.py
funga_eth.egg-info/PKG-INFO
funga_eth.egg-info/SOURCES.txt
funga_eth.egg-info/dependency_links.txt
funga_eth.egg-info/entry_points.txt
funga_eth.egg-info/requires.txt
funga_eth.egg-info/top_level.txt
tests/test_cli.py
tests/test_keystore_dict.py
tests/test_pbkdf2.py
tests/test_sign.py
tests/test_socket.py