Metadata-Version: 2.1
Name: funga-eth
Version: 0.7.2
Summary: Ethereum implementation of the funga keystore and signer
Home-page: https://git.defalsify.org/funga-eth
Author: Louis Holbrook
Author-email: dev@holbrook.no
License: AGPLv3+
Classifier: Programming Language :: Python :: 3
Classifier: Operating System :: OS Independent
Classifier: Development Status :: 4 - Beta
Classifier: Intended Audience :: Developers
Classifier: Topic :: Software Development :: Libraries
Classifier: Environment :: Console
Classifier: License :: OSI Approved :: GNU Affero General Public License v3 or later (AGPLv3+)
Provides-Extra: sql
License-File: LICENSE
